ciphercrackerMSWA02/__init__.py
ciphercrackerMSWA02/cipherCracker.py
ciphercrackerMSWA02/data/mladik_z_povolani.txt
ciphercrackermswa02-0.1.4.dist-info/METADATA
ciphercrackermswa02-0.1.4.dist-info/WHEEL
ciphercrackermswa02-0.1.4.dist-info/top_level.txt
ciphercrackermswa02-0.1.4.dist-info/RECORD
