Metadata-Version: 2.4
Name: ciphercrackerMSWA02
Version: 0.1.4
Summary: monoalphabetic substitution cipher cracking
Home-page: https://github.com/MSWA-02/python_semestral.git
Author: Oskar Šefců et al.
Author-email: oskysef@gmail.com
Classifier: Programming Language :: Python :: 3
Classifier: License :: OSI Approved :: MIT License
Requires-Python: >=3.6
Dynamic: author
Dynamic: author-email
Dynamic: classifier
Dynamic: description
Dynamic: description-content-type
Dynamic: home-page
Dynamic: requires-python
Dynamic: summary
